{
  "id": "astia-100f",
  "name": "Fuji Astia 100F",
  "description": "Soft contrast slide film optimized for skin tones and fashion photography",
  "category": "Slide Film",
  "thumbnail": "thumbnails/astia100f.jpg",
  "parameters": {
    "colorMatrix": [
      [1.10, -0.05, -0.05],
      [-0.05, 1.08, -0.03],
      [-0.05, -0.03, 1.08]
    ],
    "toneCurve": {
      "red": [[0, 5], [64, 65], [128, 128], [192, 190], [255, 250]],
      "green": [[0, 5], [64, 65], [128, 128], [192, 190], [255, 250]],
      "blue": [[0, 5], [64, 65], [128, 128], [192, 190], [255, 250]]
    },
    "grainParams": {
      "intensity": 12,
      "size": 0.6,
      "roughness": 0.4
    },
    "colorBalance": {
      "redShift": 5,
      "greenShift": 0,
      "blueShift": 0,
      "redBalance": 1.05,
      "greenBalance": 1.00,
      "blueBalance": 0.98
    },
    "dynamicRange": {
      "compression": 0.85,
      "shadowPreservation": 0.5,
      "highlightRolloff": 0.7
    }
  }
}